hyperparams/__init__.py
hyperparams/hyperparams.py
test/__init__.py
test/test_load.py
test/test_pyparams.py
test/data/__init__.py
test/data/params.py
hyperparams-1.2.3.dist-info/LICENSE
hyperparams-1.2.3.dist-info/METADATA
hyperparams-1.2.3.dist-info/WHEEL
hyperparams-1.2.3.dist-info/top_level.txt
hyperparams-1.2.3.dist-info/RECORD
