Metadata-Version: 2.1
Name: hyperparams
Version: 1.2.3
Summary: A simple hyperparameters handler object.
Home-page: https://github.com/penguinmenac3/hyperparams
Author: Michael Fuerst
Author-email: mail@michaelfuerst.de
License: BSD
Download-URL: https://github.com/penguinmenac3/hyperparams/tarball/1.2.3
Platform: UNKNOWN
Classifier: Development Status :: 3 - Alpha
Classifier: Intended Audience :: Developers
Classifier: Programming Language :: Python
Requires-Dist: jsmin
